tfgating/__init__.py
tfgating/run.py
tfgating/tfgating.py
tfgating/utils.py
tfgating/version.py
tfgating-0.1.0a0.dist-info/LICENSE
tfgating-0.1.0a0.dist-info/METADATA
tfgating-0.1.0a0.dist-info/WHEEL
tfgating-0.1.0a0.dist-info/entry_points.txt
tfgating-0.1.0a0.dist-info/top_level.txt
tfgating-0.1.0a0.dist-info/RECORD
