Metadata-Version: 2.1
Name: tfgating
Version: 0.1.0a0
Summary: A TensorFlow-based implementation of Spectral Gating, an algorithm for denoising audio signals
Home-page: https://github.com/noisereduce/TFSpectralGating
Author: Asaf Zorea
Author-email: zoreasaf@gmail.com
License: MIT
Classifier: Programming Language :: Python :: 3
Classifier: License :: OSI Approved :: MIT License
Classifier: Operating System :: OS Independent
Requires-Python: >=3.6
License-File: LICENSE
Requires-Dist: matplotlib
Requires-Dist: numpy
Requires-Dist: soundfile
Requires-Dist: tensorflow
